bakatrouble_pony_migrate-0.8.dev0.dist-info/METADATA
bakatrouble_pony_migrate-0.8.dev0.dist-info/RECORD
bakatrouble_pony_migrate-0.8.dev0.dist-info/WHEEL
bakatrouble_pony_migrate-0.8.dev0.dist-info/top_level.txt
pony/__init__.py
pony/converting.py
pony/options.py
pony/py23compat.py
pony/editor/__init__.py
pony/editor/__main__.py
pony/editor/diagram.py
pony/editor/placing.py
pony/editor/util.py
pony/migrate/__init__.py
pony/migrate/command.py
pony/migrate/diagram_ops.py
pony/migrate/exceptions.py
pony/migrate/executor.py
pony/migrate/migration.py
pony/migrate/operations.py
pony/migrate/questioner.py
pony/migrate/serializer.py
pony/migrate/utils.py
pony/migrate/writer.py
pony/orm/__init__.py
pony/orm/asttranslation.py
pony/orm/core.py
pony/orm/dbapiprovider.py
pony/orm/dbschema.py
pony/orm/decompiling.py
pony/orm/ormtypes.py
pony/orm/serialization.py
pony/orm/sqlbuilding.py
pony/orm/sqlsymbols.py
pony/orm/sqltranslation.py
pony/orm/dbproviders/__init__.py
pony/orm/dbproviders/mysql.py
pony/orm/dbproviders/oracle.py
pony/orm/dbproviders/postgres.py
pony/orm/dbproviders/sqlite.py
pony/orm/examples/__init__.py
pony/orm/examples/bottle_example.py
pony/orm/examples/compositekeys.py
pony/orm/examples/demo.py
pony/orm/examples/estore.py
pony/orm/examples/inheritance1.py
pony/orm/examples/migrations_example.py
pony/orm/examples/test_numbers.py
pony/orm/examples/test_operations.py
pony/orm/examples/university1.py
pony/orm/examples/university2.py
pony/orm/integration/__init__.py
pony/orm/integration/bottle_plugin.py
pony/orm/tests/__init__.py
pony/orm/tests/fixtures.py
pony/orm/tests/model1.py
pony/orm/tests/sql_tests.py
pony/orm/tests/test_autostrip.py
pony/orm/tests/test_bug_170.py
pony/orm/tests/test_bug_182.py
pony/orm/tests/test_bug_331.py
pony/orm/tests/test_collections.py
pony/orm/tests/test_core_find_in_cache.py
pony/orm/tests/test_core_multiset.py
pony/orm/tests/test_crud.py
pony/orm/tests/test_crud_raw_sql.py
pony/orm/tests/test_db_session.py
pony/orm/tests/test_declarative_attr_set_monad.py
pony/orm/tests/test_declarative_date.py
pony/orm/tests/test_declarative_exceptions.py
