Metadata-Version: 2.1
Name: bakatrouble-pony-migrate
Version: 0.8.dev0
Summary: Pony Object-Relational Mapper
Home-page: https://ponyorm.com
Author: Alexander Kozlovsky, Alexey Malashkevich
Author-email: team@ponyorm.com
License: Apache License Version 2.0
Download-URL: http://pypi.python.org/pypi/bakatrouble_pony_migrate/
Platform: UNKNOWN
Classifier: Development Status :: 4 - Beta
Classifier: Intended Audience :: Developers
Classifier: License :: OSI Approved :: Apache Software License
Classifier: Operating System :: OS Independent
Classifier: Programming Language :: Python
Classifier: Programming Language :: Python :: 2
Classifier: Programming Language :: Python :: 2.7
Classifier: Programming Language :: Python :: 3
Classifier: Programming Language :: Python :: 3.3
Classifier: Programming Language :: Python :: 3.4
Classifier: Programming Language :: Python :: 3.5
Classifier: Programming Language :: Python :: 3.6
Classifier: Topic :: Software Development :: Libraries
Classifier: Topic :: Database
Requires-Dist: docopt
